slovene_text_preprocessing/__init__.py
slovene_text_preprocessing/ipa.py
slovene_text_preprocessing/unify_chars.py
slovene_text_preprocessing-0.0.3.dist-info/METADATA
slovene_text_preprocessing-0.0.3.dist-info/WHEEL
slovene_text_preprocessing-0.0.3.dist-info/top_level.txt
slovene_text_preprocessing-0.0.3.dist-info/RECORD
