Metadata-Version: 2.1
Name: slovene-text-preprocessing
Version: 0.0.3
Summary: slovenian text preprocessing
Home-page: UNKNOWN
Author: Peter Pisljar
License: UNKNOWN
Platform: UNKNOWN
Requires-Python: >=3.8.0, <3.12
Requires-Dist: obeliks
